{"statistics": [{"period": "ALL", "groups": [{"groupName": "Possession", "statisticsItems": [{"name": "Ball possession", "home": "47%", "away": "53%", "compareCode": 2, "statisticsType": "positive", "valueType": "event", "homeValue": 47, "awayValue": 53}]}, {"groupName": "Shots", "statisticsItems": [{"name": "Total shots", "home": "16", "away": "7", "compareCode": 1, "statisticsType": "positive", "valueType": "event", "homeValue": 16, "awayValue": 7}, {"name": "Shots on target", "home": "5", "away": "2", "compareCode": 1, "statisticsType": "positive", "valueType": "event", "homeValue": 5, "awayValue": 2}, {"name": "Shots off target", "home": "7", "away": "4", "compareCode": 1, "statisticsType": "negative", "valueType": "event", "homeValue": 7, "awayValue": 4}, {"name": "Blocked shots", "home": "4", "away": "1", "compareCode": 1, "statisticsType": "negative", "valueType": "event", "homeValue": 4, "awayValue": 1}]}, {"groupName": "TVData", "statisticsItems": [{"name": "Corner kicks", "home": "1", "away": "2", "compareCode": 2, "statisticsType": "positive", "valueType": "event", "homeValue": 1, "awayValue": 2}, {"name": "Offsides", "home": "2", "away": "1", "compareCode": 1, "statisticsType": "negative", "valueType": "event", "homeValue": 2, "awayValue": 1}, {"name": "Fouls", "home": "16", "away": "11", "compareCode": 1, "statisticsType": "negative", "valueType": "event", "homeValue": 16, "awayValue": 11}, {"name": "Yellow cards", "home": "3", "away": "3", "compareCode": 3, "statisticsType": "negative", "valueType": "event", "homeValue": 3, "awayValue": 3}, {"name": "Free kicks", "home": "10", "away": "14", "compareCode": 2, "statisticsType": "positive", "valueType": "event", "homeValue": 10, "awayValue": 14}, {"name": "Throw-ins", "home": "18", "away": "22", "compareCode": 2, "statisticsType": "positive", "valueType": "event", "homeValue": 18, "awayValue": 22}, {"name": "Goal kicks", "home": "4", "away": "10", "compareCode": 2, "statisticsType": "positive", "valueType": "event", "homeValue": 4, "awayValue": 10}]}, {"groupName": "Shots extra", "statisticsItems": [{"name": "Big chances", "home": "1", "away": "0", "compareCode": 1, "statisticsType": "positive", "valueType": "event", "homeValue": 1, "awayValue": 0}, {"name": "Big chances missed", "home": "1", "away": "0", "compareCode": 1, "statisticsType": "negative", "valueType": "event", "homeValue": 1, "awayValue": 0}, {"name": "Hit woodwork", "home": "0", "away": "1", "compareCode": 2, "statisticsType": "negative", "valueType": "event", "homeValue": 0, "awayValue": 1}, {"name": "Counter attacks", "home": "4", "away": "0", "compareCode": 1, "statisticsType": "positive", "valueType": "event", "homeValue": 4, "awayValue": 0}, {"name": "Counter attack shots", "home": "3", "away": "0", "compareCode": 1, "statisticsType": "positive", "valueType": "event", "homeValue": 3, "awayValue": 0}, {"name": "Counter attack goals", "home": "1", "away": "0", "compareCode": 1, "statisticsType": "positive", "valueType": "event", "homeValue": 1, "awayValue": 0}, {"name": "Shots inside box", "home": "7", "away": "3", "compareCode": 1, "statisticsType": "positive", "valueType": "event", "homeValue": 7, "awayValue": 3}, {"name": "Shots outside box", "home": "9", "away": "4", "compareCode": 1, "statisticsType": "positive", "valueType": "event", "homeValue": 9, "awayValue": 4}, {"name": "Goalkeeper saves", "home": "2", "away": "2", "compareCode": 3, "statisticsType": "positive", "valueType": "event", "homeValue": 2, "awayValue": 2}]}, {"groupName": "Passes", "statisticsItems": [{"name": "Passes", "home": "274", "away": "309", "compareCode": 2, "statisticsType": "positive", "valueType": "event", "homeValue": 274, "awayValue": 309}, {"name": "Accurate passes", "home": "212 (77%)", "away": "241 (78%)", "compareCode": 2, "statisticsType": "positive", "valueType": "event", "homeValue": 212, "awayValue": 241}, {"name": "Long balls", "home": "34/67 (51%)", "away": "21/42 (50%)", "compareCode": 1, "statisticsType": "positive", "valueType": "team", "homeValue": 34, "awayValue": 21, "homeTotal": 67, "awayTotal": 42}, {"name": "Crosses", "home": "3/10 (30%)", "away": "1/13 (8%)", "compareCode": 1, "statisticsType": "positive", "valueType": "team", "homeValue": 3, "awayValue": 1, "homeTotal": 10, "awayTotal": 13}]}, {"groupName": "Duels", "statisticsItems": [{"name": "Dribbles", "home": "10/21 (48%)", "away": "11/20 (55%)", "compareCode": 2, "statisticsType": "positive", "valueType": "team", "homeValue": 10, "awayValue": 11, "homeTotal": 21, "awayTotal": 20}, {"name": "Possession lost", "home": "101", "away": "114", "compareCode": 2, "statisticsType": "negative", "valueType": "event", "homeValue": 101, "awayValue": 114}, {"name": "Duels won", "home": "52", "away": "48", "compareCode": 1, "statisticsType": "positive", "valueType": "event", "homeValue": 52, "awayValue": 48}, {"name": "Aerials won", "home": "17", "away": "10", "compareCode": 1, "statisticsType": "positive", "valueType": "event", "homeValue": 17, "awayValue": 10}]}, {"groupName": "Defending", "statisticsItems": [{"name": "Tackles", "home": "15", "away": "13", "compareCode": 1, "statisticsType": "positive", "valueType": "event", "homeValue": 15, "awayValue": 13}, {"name": "Interceptions", "home": "8", "away": "4", "compareCode": 1, "statisticsType": "positive", "valueType": "event", "homeValue": 8, "awayValue": 4}, {"name": "Clearances", "home": "14", "away": "14", "compareCode": 3, "statisticsType": "positive", "valueType": "event", "homeValue": 14, "awayValue": 14}]}]}, {"period": "1ST", "groups": [{"groupName": "Possession", "statisticsItems": [{"name": "Ball possession", "home": "50%", "away": "50%", "compareCode": 3, "statisticsType": "positive", "valueType": "event", "homeValue": 50, "awayValue": 50}]}, {"groupName": "Shots", "statisticsItems": [{"name": "Total shots", "home": "9", "away": "0", "compareCode": 1, "statisticsType": "positive", "valueType": "event", "homeValue": 9, "awayValue": 0}, {"name": "Shots on target", "home": "2", "away": "0", "compareCode": 1, "statisticsType": "positive", "valueType": "event", "homeValue": 2, "awayValue": 0}, {"name": "Shots off target", "home": "4", "away": "0", "compareCode": 1, "statisticsType": "negative", "valueType": "event", "homeValue": 4, "awayValue": 0}, {"name": "Blocked shots", "home": "3", "away": "0", "compareCode": 1, "statisticsType": "negative", "valueType": "event", "homeValue": 3, "awayValue": 0}]}, {"groupName": "TVData", "statisticsItems": [{"name": "Corner kicks", "home": "1", "away": "0", "compareCode": 1, "statisticsType": "positive", "valueType": "event", "homeValue": 1, "awayValue": 0}, {"name": "Offsides", "home": "1", "away": "0", "compareCode": 1, "statisticsType": "negative", "valueType": "event", "homeValue": 1, "awayValue": 0}, {"name": "Yellow cards", "home": "0", "away": "1", "compareCode": 2, "statisticsType": "negative", "valueType": "event", "homeValue": 0, "awayValue": 1}, {"name": "Free kicks", "home": "5", "away": "5", "compareCode": 3, "statisticsType": "positive", "valueType": "event", "homeValue": 5, "awayValue": 5}, {"name": "Throw-ins", "home": "7", "away": "12", "compareCode": 2, "statisticsType": "positive", "valueType": "event", "homeValue": 7, "awayValue": 12}, {"name": "Goal kicks", "home": "1", "away": "6", "compareCode": 2, "statisticsType": "positive", "valueType": "event", "homeValue": 1, "awayValue": 6}]}, {"groupName": "Shots extra", "statisticsItems": [{"name": "Big chances", "home": "1", "away": "0", "compareCode": 1, "statisticsType": "positive", "valueType": "event", "homeValue": 1, "awayValue": 0}, {"name": "Big chances missed", "home": "1", "away": "0", "compareCode": 1, "statisticsType": "negative", "valueType": "event", "homeValue": 1, "awayValue": 0}, {"name": "Hit woodwork", "home": "0", "away": "0", "compareCode": 3, "statisticsType": "negative", "valueType": "event", "homeValue": 0, "awayValue": 0}, {"name": "Counter attacks", "home": "3", "away": "0", "compareCode": 1, "statisticsType": "positive", "valueType": "event", "homeValue": 3, "awayValue": 0}, {"name": "Counter attack shots", "home": "2", "away": "0", "compareCode": 1, "statisticsType": "positive", "valueType": "event", "homeValue": 2, "awayValue": 0}, {"name": "Counter attack goals", "home": "1", "away": "0", "compareCode": 1, "statisticsType": "positive", "valueType": "event", "homeValue": 1, "awayValue": 0}, {"name": "Shots inside box", "home": "4", "away": "0", "compareCode": 1, "statisticsType": "positive", "valueType": "event", "homeValue": 4, "awayValue": 0}, {"name": "Shots outside box", "home": "5", "away": "0", "compareCode": 1, "statisticsType": "positive", "valueType": "event", "homeValue": 5, "awayValue": 0}, {"name": "Goalkeeper saves", "home": "0", "away": "0", "compareCode": 3, "statisticsType": "positive", "valueType": "event", "homeValue": 0, "awayValue": 0}]}, {"groupName": "Passes", "statisticsItems": [{"name": "Passes", "home": "169", "away": "175", "compareCode": 2, "statisticsType": "positive", "valueType": "event", "homeValue": 169, "awayValue": 175}, {"name": "Accurate passes", "home": "138 (82%)", "away": "141 (81%)", "compareCode": 1, "statisticsType": "positive", "valueType": "event", "homeValue": 138, "awayValue": 141}, {"name": "Long balls", "home": "21/36 (58%)", "away": "6/15 (40%)", "compareCode": 1, "statisticsType": "positive", "valueType": "team", "homeValue": 21, "awayValue": 6, "homeTotal": 36, "awayTotal": 15}, {"name": "Crosses", "home": "1/7 (14%)", "away": "0/2 (0%)", "compareCode": 1, "statisticsType": "positive", "valueType": "team", "homeValue": 1, "awayValue": 0, "homeTotal": 7, "awayTotal": 2}]}, {"groupName": "Duels", "statisticsItems": [{"name": "Dribbles", "home": "6/13 (46%)", "away": "5/11 (45%)", "compareCode": 1, "statisticsType": "positive", "valueType": "team", "homeValue": 6, "awayValue": 5, "homeTotal": 13, "awayTotal": 11}, {"name": "Possession lost", "home": "52", "away": "57", "compareCode": 2, "statisticsType": "negative", "valueType": "event", "homeValue": 52, "awayValue": 57}, {"name": "Duels won", "home": "28", "away": "20", "compareCode": 1, "statisticsType": "positive", "valueType": "event", "homeValue": 28, "awayValue": 20}, {"name": "Aerials won", "home": "7", "away": "2", "compareCode": 1, "statisticsType": "positive", "valueType": "event", "homeValue": 7, "awayValue": 2}]}, {"groupName": "Defending", "statisticsItems": [{"name": "Tackles", "home": "10", "away": "8", "compareCode": 1, "statisticsType": "positive", "valueType": "event", "homeValue": 10, "awayValue": 8}, {"name": "Interceptions", "home": "6", "away": "1", "compareCode": 1, "statisticsType": "positive", "valueType": "event", "homeValue": 6, "awayValue": 1}, {"name": "Clearances", "home": "2", "away": "8", "compareCode": 2, "statisticsType": "positive", "valueType": "event", "homeValue": 2, "awayValue": 8}]}]}, {"period": "2ND", "groups": [{"groupName": "Possession", "statisticsItems": [{"name": "Ball possession", "home": "42%", "away": "58%", "compareCode": 2, "statisticsType": "positive", "valueType": "event", "homeValue": 42, "awayValue": 58}]}, {"groupName": "Shots", "statisticsItems": [{"name": "Total shots", "home": "7", "away": "7", "compareCode": 3, "statisticsType": "positive", "valueType": "event", "homeValue": 7, "awayValue": 7}, {"name": "Shots on target", "home": "3", "away": "2", "compareCode": 1, "statisticsType": "positive", "valueType": "event", "homeValue": 3, "awayValue": 2}, {"name": "Shots off target", "home": "3", "away": "4", "compareCode": 2, "statisticsType": "negative", "valueType": "event", "homeValue": 3, "awayValue": 4}, {"name": "Blocked shots", "home": "1", "away": "1", "compareCode": 3, "statisticsType": "negative", "valueType": "event", "homeValue": 1, "awayValue": 1}]}, {"groupName": "TVData", "statisticsItems": [{"name": "Corner kicks", "home": "0", "away": "2", "compareCode": 2, "statisticsType": "positive", "valueType": "event", "homeValue": 0, "awayValue": 2}, {"name": "Offsides", "home": "1", "away": "1", "compareCode": 3, "statisticsType": "negative", "valueType": "event", "homeValue": 1, "awayValue": 1}, {"name": "Yellow cards", "home": "3", "away": "2", "compareCode": 1, "statisticsType": "negative", "valueType": "event", "homeValue": 3, "awayValue": 2}, {"name": "Free kicks", "home": "5", "away": "9", "compareCode": 2, "statisticsType": "positive", "valueType": "event", "homeValue": 5, "awayValue": 9}, {"name": "Throw-ins", "home": "11", "away": "10", "compareCode": 1, "statisticsType": "positive", "valueType": "event", "homeValue": 11, "awayValue": 10}, {"name": "Goal kicks", "home": "3", "away": "4", "compareCode": 2, "statisticsType": "positive", "valueType": "event", "homeValue": 3, "awayValue": 4}]}, {"groupName": "Shots extra", "statisticsItems": [{"name": "Big chances", "home": "0", "away": "0", "compareCode": 3, "statisticsType": "positive", "valueType": "event", "homeValue": 0, "awayValue": 0}, {"name": "Big chances missed", "home": "0", "away": "0", "compareCode": 3, "statisticsType": "negative", "valueType": "event", "homeValue": 0, "awayValue": 0}, {"name": "Hit woodwork", "home": "0", "away": "1", "compareCode": 2, "statisticsType": "negative", "valueType": "event", "homeValue": 0, "awayValue": 1}, {"name": "Counter attacks", "home": "1", "away": "0", "compareCode": 1, "statisticsType": "positive", "valueType": "event", "homeValue": 1, "awayValue": 0}, {"name": "Counter attack shots", "home": "1", "away": "0", "compareCode": 1, "statisticsType": "positive", "valueType": "event", "homeValue": 1, "awayValue": 0}, {"name": "Counter attack goals", "home": "0", "away": "0", "compareCode": 3, "statisticsType": "positive", "valueType": "event", "homeValue": 0, "awayValue": 0}, {"name": "Shots inside box", "home": "3", "away": "3", "compareCode": 3, "statisticsType": "positive", "valueType": "event", "homeValue": 3, "awayValue": 3}, {"name": "Shots outside box", "home": "4", "away": "4", "compareCode": 3, "statisticsType": "positive", "valueType": "event", "homeValue": 4, "awayValue": 4}, {"name": "Goalkeeper saves", "home": "2", "away": "2", "compareCode": 3, "statisticsType": "positive", "valueType": "event", "homeValue": 2, "awayValue": 2}]}, {"groupName": "Passes", "statisticsItems": [{"name": "Passes", "home": "105", "away": "134", "compareCode": 2, "statisticsType": "positive", "valueType": "event", "homeValue": 105, "awayValue": 134}, {"name": "Accurate passes", "home": "74 (70%)", "away": "100 (75%)", "compareCode": 2, "statisticsType": "positive", "valueType": "event", "homeValue": 74, "awayValue": 100}, {"name": "Long balls", "home": "13/31 (42%)", "away": "15/27 (56%)", "compareCode": 2, "statisticsType": "positive", "valueType": "team", "homeValue": 13, "awayValue": 15, "homeTotal": 31, "awayTotal": 27}, {"name": "Crosses", "home": "2/3 (67%)", "away": "1/11 (9%)", "compareCode": 1, "statisticsType": "positive", "valueType": "team", "homeValue": 2, "awayValue": 1, "homeTotal": 3, "awayTotal": 11}]}, {"groupName": "Duels", "statisticsItems": [{"name": "Dribbles", "home": "4/8 (50%)", "away": "6/9 (67%)", "compareCode": 2, "statisticsType": "positive", "valueType": "team", "homeValue": 4, "awayValue": 6, "homeTotal": 8, "awayTotal": 9}, {"name": "Possession lost", "home": "49", "away": "57", "compareCode": 2, "statisticsType": "negative", "valueType": "event", "homeValue": 49, "awayValue": 57}, {"name": "Duels won", "home": "24", "away": "28", "compareCode": 2, "statisticsType": "positive", "valueType": "event", "homeValue": 24, "awayValue": 28}, {"name": "Aerials won", "home": "10", "away": "8", "compareCode": 1, "statisticsType": "positive", "valueType": "event", "homeValue": 10, "awayValue": 8}]}, {"groupName": "Defending", "statisticsItems": [{"name": "Tackles", "home": "5", "away": "5", "compareCode": 3, "statisticsType": "positive", "valueType": "event", "homeValue": 5, "awayValue": 5}, {"name": "Interceptions", "home": "2", "away": "3", "compareCode": 2, "statisticsType": "positive", "valueType": "event", "homeValue": 2, "awayValue": 3}, {"name": "Clearances", "home": "12", "away": "6", "compareCode": 1, "statisticsType": "positive", "valueType": "event", "homeValue": 12, "awayValue": 6}]}]}]}